{
  "youtubeId": "16AbnwFyhVU",
  "title": "cocoon - Insight In An Unseizable World | Demoscene",
  "lastFetched": "2025-11-29T12:39:35.931Z",
  "ai": {
    "title": "Insight In An Unseizable World",
    "artist": "cocoon"
  },
  "lastfm": {
    "id": "Cocoon/_/Insight+In+An+Unseizable+World",
    "listeners": 9,
    "playcount": 9,
    "title": "Insight In An Unseizable World",
    "artist": "Cocoon",
    "tags": [
      "folk",
      "indie",
      "french",
      "acoustic",
      "indie folk"
    ]
  },
  "youtube": {
    "title": "cocoon - Insight In An Unseizable World | Demoscene",
    "channel": "TheDemoTube"
  }
}