{
  "youtubeId": "1JKAoIYGhX8",
  "title": "Darkhorse",
  "artist": "Emma Ruth Rundle",
  "lastFetched": "2025-12-02T00:34:35.973Z",
  "odesli": {
    "amazonMusic": "B0F4VPGJB7",
    "amazonStore": "B0F4VPGJB7",
    "pandora": "TR:12912849",
    "soundcloud": "emmaruthrundleofficial/darkhorse",
    "tidal": "430143675",
    "youtube": "1JKAoIYGhX8",
    "youtubeMusic": "1JKAoIYGhX8"
  },
  "musicbrainz": {
    "artistTags": [
      "ambient",
      "contemporary folk",
      "dream pop",
      "experimental",
      "folk",
      "folk rock",
      "post-rock",
      "singer-songwriter"
    ],
    "artistGenres": [
      "ambient",
      "contemporary folk",
      "dream pop",
      "experimental",
      "folk"
    ],
    "trackMbid": "037199d4-6789-43a3-8933-8e2ba1ccb8eb",
    "artistMbid": "7ba593b9-79d4-4860-92c8-ade2a1ef4551",
    "artistCountry": "US",
    "externalIdsArtist": {
      "allmusic": "mn0002423072",
      "bandcamp": "https://emmaruthrundle.bandcamp.com/",
      "discogs": "1782496",
      "spotify": "34gLicNdz493863yZTanvC",
      "deezer": "5799810",
      "lastfm": "Emma+Ruth+Rundle",
      "genius": "Emma-ruth-rundle",
      "rateyourmusic": "emma-ruth-rundle",
      "soundcloud": "https://soundcloud.com/emmaruthrundleofficial",
      "wikidata": "Q17411149",
      "youtube": "UCXqoHeiHh7wX-ZGoknAsnDA"
    }
  },
  "lastfm": {
    "id": "Emma+Ruth+Rundle/_/Darkhorse",
    "listeners": 50653,
    "playcount": 331192,
    "tags": [
      "singer-songwriter",
      "shoegaze",
      "post-rock",
      "dream pop",
      "horse lied"
    ]
  }
}