{
  "youtubeId": "2vbf2qRJocc",
  "title": "Come About",
  "artist": "Love'n'Joy",
  "lastFetched": "2025-11-19T14:38:16.319Z",
  "odesli": {
    "amazonMusic": "B07B2BB9SS",
    "amazonStore": "B07B2BB9SS",
    "boomplay": "4838790",
    "pandora": "TR:56668228",
    "soundcloud": "lovenjoyband/lovenjoy-come-about",
    "tidal": "103044896",
    "youtube": "2vbf2qRJocc",
    "youtubeMusic": "2vbf2qRJocc"
  },
  "mbid": "8a75d462-a8ba-4f65-921f-694e09c3e8ed",
  "artistMbid": "015e7f44-fbdb-4fae-8a9a-b406cb0b1234",
  "lastfm": {
    "id": "Love%27n%27Joy/_/Come+About",
    "listeners": 1192,
    "playcount": 4030
  }
}