{
  "youtubeId": "_K_PMVdb-c0",
  "title": "TS5_ Béla Fleck - Big Country.mp4",
  "lastFetched": "2025-11-26T10:55:48.911Z",
  "ai": {
    "title": "Big Country",
    "artist": "Béla Fleck"
  },
  "lastfm": {
    "id": "B%C3%A9la+Fleck/_/Big+Country",
    "listeners": 3687,
    "playcount": 13665,
    "title": "Big Country",
    "artist": "Béla Fleck",
    "mbid": "1a528c9d-9c8d-42ef-8f88-017d1f0ed5c3",
    "artistMbid": "e1a889b7-5e45-447f-baa0-b9c6cbc0d39f",
    "tags": [
      "bluegrass",
      "banjo",
      "jazz",
      "instrumental",
      "fusion"
    ]
  }
}