{
  "youtubeId": "C8fIVTH0TiM",
  "title": "MOVITS! - Äppelknyckarjazz Video (Officiell)",
  "lastFetched": "2025-11-30T20:21:37.137Z",
  "ai": {
    "title": "Äppelknyckarjazz",
    "artist": "MOVITS!"
  },
  "lastfm": {
    "id": "Movits%21/_/%C3%84ppelknyckarjazz",
    "listeners": 31098,
    "playcount": 194934,
    "title": "Äppelknyckarjazz",
    "artist": "Movits!",
    "mbid": "30d4b096-c0e2-3644-93a2-d78184c6f5fe",
    "artistMbid": "d74c95e2-f779-43e4-9e1d-6fbaaf0c6bae",
    "tags": [
      "lugnt03-",
      "swedish",
      "lugnt03"
    ]
  },
  "musicbrainz": {
    "trackMbid": "a19d4b50-00e0-4efb-9979-e10075374cd9",
    "artistMbid": "d74c95e2-f779-43e4-9e1d-6fbaaf0c6bae",
    "releaseCount": 2,
    "artistGenres": [
      "alternative hip hop",
      "swing"
    ]
  }
}