{
  "youtubeId": "DRdMHbzjrlU",
  "title": "Nuke Em",
  "artist": "Datsik",
  "lastFetched": "2025-11-28T18:36:34.895Z",
  "odesli": {
    "pandora": "TR:28513934",
    "soundcloud": "sound-of-dubstep/datsik-nuke-em",
    "spotify": "6vqnddLZgmg7EmvjnNMdnx",
    "tidal": "61497783",
    "youtube": "DRdMHbzjrlU",
    "youtubeMusic": "DRdMHbzjrlU"
  },
  "lastfm": {
    "id": "Datsik/_/Nuke+Em",
    "listeners": 11795,
    "playcount": 36895,
    "title": "Nuke Em",
    "artist": "Datsik",
    "tags": [
      "dubstep"
    ]
  }
}