{
  "youtubeId": "HPHdCroE0fY",
  "title": "Onprangering",
  "artist": "die ärzte",
  "lastFetched": "2025-12-02T00:58:54.375Z",
  "odesli": {
    "amazonMusic": "B08C268ZX8",
    "amazonStore": "B08C268ZX8",
    "appleMusic": "1521301391",
    "itunes": "1521301391",
    "pandora": "TR:33580404",
    "spotify": "0cB0e8kDJMnOl5wlw1tRsX",
    "tidal": "146882729",
    "youtube": "HPHdCroE0fY",
    "youtubeMusic": "HPHdCroE0fY"
  },
  "lastfm": {
    "id": "Die+%C3%84rzte/_/Onprangering",
    "listeners": 19968,
    "playcount": 84820,
    "title": "Onprangering",
    "artist": "Die Ärzte",
    "mbid": "05910234-54a5-3265-baee-f756eb57aae7",
    "artistMbid": "f2fb0ff0-5679-42ec-a55c-15109ce6e320",
    "tags": [
      "german",
      "deutsch",
      "german artist",
      "punk"
    ]
  },
  "musicbrainz": {
    "trackMbid": "86303fe9-a857-47b2-94bc-0fb6ad128c88",
    "artistMbid": "f2fb0ff0-5679-42ec-a55c-15109ce6e320",
    "releaseCount": 3,
    "genres": [
      "punk"
    ],
    "artistGenres": [
      "neue deutsche welle",
      "pop punk",
      "punk",
      "punk rock",
      "rock"
    ],
    "releasedAt": "2000-10-23",
    "artistCountry": "DE",
    "externalIdsArtist": {
      "allmusic": "mn0000823202",
      "discogs": "45317",
      "spotify": "0cbL6CYnRqpAxf1evwUVQD",
      "deezer": "2154",
      "lastfm": "Die+%C3%84rzte",
      "genius": "Die-arzte",
      "rateyourmusic": "die_arzte",
      "soundcloud": "https://soundcloud.com/diearzte",
      "wikidata": "Q32645",
      "youtube": "UCsJsxj9pPP8sZuaRiaNAavQ"
    }
  }
}