{
  "youtubeId": "jP4-XrbGt3M",
  "title": "Sowieso",
  "artist": "Mark Forster",
  "lastFetched": "2025-12-02T01:43:00.316Z",
  "odesli": {
    "amazonMusic": "B01GB0YIOG",
    "amazonStore": "B01GB0YIOG",
    "pandora": "TR:29122379",
    "soundcloud": "mark-forster-official/sowieso",
    "spotify": "1CLljfgtXG6ODaJONSMkwQ",
    "tidal": "80995211",
    "yandex": "29126106",
    "youtube": "jP4-XrbGt3M",
    "youtubeMusic": "jP4-XrbGt3M"
  },
  "lastfm": {
    "id": "Mark+Forster/_/Sowieso",
    "listeners": 15762,
    "playcount": 105661,
    "title": "Sowieso",
    "artist": "Mark Forster",
    "mbid": "1c12156e-a14a-4dfc-b0c3-ca196466f745",
    "artistMbid": "002341a0-ff46-4ec1-86b2-34eea3c15ed3",
    "tags": [
      "german",
      "linedance 2016",
      "2017 single"
    ]
  },
  "musicbrainz": {
    "trackMbid": "58630fae-5051-4e40-b1e2-286889418167",
    "artistMbid": "82931296-9466-447f-a7af-8f3a856bcfd9",
    "releaseCount": 14,
    "genres": [
      "pop"
    ],
    "artistGenres": [
      "pop"
    ],
    "releasedAt": "2016-06-03",
    "artistCountry": "DE",
    "externalIdsArtist": {
      "allmusic": "mn0002921153",
      "bandcamp": "https://mark-forster.bandcamp.com/",
      "discogs": "3195385",
      "spotify": "7qXzy6c5RWT0XlVQcOBIDG",
      "deezer": "2163861",
      "lastfm": "Mark+Forster",
      "rateyourmusic": "mark_forster",
      "soundcloud": "https://soundcloud.com/mark-forster-official",
      "wikidata": "Q105558",
      "youtube": "UCLyAYe-pk6HGmfyT94ouBcA"
    }
  },
  "youtube": {
    "title": "Mark Forster - Sowieso (Official Video)",
    "channel": "Mark Forster"
  }
}