{
  "youtubeId": "kDhptBT_-VI",
  "title": "Vai malandra (feat. Tropkillaz & DJ Yuri Martins)",
  "artist": "Anitta",
  "lastFetched": "2025-11-30T17:43:16.359Z",
  "odesli": {
    "amazonMusic": "B0787LHX1S",
    "amazonStore": "B0787LHX1S",
    "audiomack": "10226596",
    "anghami": "1109612067",
    "deezer": "440092662",
    "appleMusic": "1325912203",
    "itunes": "1325912203",
    "pandora": "TR:11185669",
    "soundcloud": "oficial-anitta/vai-malandra-feat-tropkillaz",
    "spotify": "6u0EAxf1OJTLS7CvInuNd7",
    "tidal": "82372427",
    "youtube": "kDhptBT_-VI",
    "youtubeMusic": "kDhptBT_-VI"
  },
  "lastfm": {
    "summary": "\"Vai Malandra\" is the 4th & last single from Brazillian singer Anitta’s project entitled Check Mate, in which she released a new song each month.\n\n\n“Vai Malandra” celebrates the freedom of expression, sexiness and empowerment of women. It highlights the energy and confidence that Anitta, Zaac and Maejor exude throughout the song. The lyrics, combined with the infectious beat and seductive melodies, create a high-energy, dynamic anthem for self-love and embracing sensuality. <a href=\"http://www.last.fm/music/Anitta/_/Vai+Malandra+(feat.+Tropkillaz+&+DJ+Yuri+Martins)\">Read more on Last.fm</a>.",
    "id": "Anitta/_/Vai+Malandra+(feat.+Tropkillaz+&+DJ+Yuri+Martins)",
    "listeners": 225873,
    "playcount": 1799677,
    "title": "Vai Malandra (feat. Tropkillaz & DJ Yuri Martins)",
    "artist": "Anitta",
    "mbid": "acbe646c-0b7d-4425-9e47-84ee93dfe2ec",
    "artistMbid": "d606b860-cc03-4959-a3fd-3a24bccf2560",
    "tags": [
      "anitta",
      "latin",
      "funk",
      "sexy"
    ]
  }
}