{
  "youtubeId": "kGW1ceFeNfE",
  "title": "Get Well Soon",
  "artist": "Reggie And The Full Effect",
  "lastFetched": "2025-11-28T18:38:59.681Z",
  "odesli": {
    "amazonMusic": "B0DZXRMYY5",
    "amazonStore": "B0DZXRMYY5",
    "appleMusic": "1441459855",
    "itunes": "1441459855",
    "soundcloud": "reggie-and-the-full-effect/get-well-soon",
    "spotify": "7zMsJkmVRIlyfnpAQgbjLx",
    "tidal": "67245982",
    "youtube": "kGW1ceFeNfE",
    "youtubeMusic": "kGW1ceFeNfE"
  },
  "lastfm": {
    "id": "Reggie+and+the+Full+Effect/_/Get+Well+Soon",
    "listeners": 72205,
    "playcount": 423384,
    "title": "Get Well Soon",
    "artist": "Reggie and the Full Effect",
    "tags": [
      "rock",
      "emo",
      "reggie and the full effect",
      "indie"
    ]
  }
}