{
  "youtubeId": "KXuyyF4yv_g",
  "title": "Hijack the Barber",
  "artist": "King Tubby",
  "lastFetched": "2025-11-30T22:26:32.883Z",
  "odesli": {
    "amazonMusic": "B00JRE1YJQ",
    "amazonStore": "B00JRE1YJQ",
    "soundcloud": "kingtubby-official/hijack-the-barber-2",
    "spotify": "67FnfU6azbK64pmbEEWNT4",
    "tidal": "10168384",
    "youtube": "KXuyyF4yv_g",
    "youtubeMusic": "KXuyyF4yv_g"
  },
  "lastfm": {
    "title": "Hijack the Barber",
    "artist": "King Tubby",
    "mbid": "9e2d2617-0372-48b0-a28b-00946e626658",
    "artistMbid": "576134a6-9f1f-4bfa-af04-4848195849ca",
    "id": "King+Tubby/_/Hijack+the+Barber",
    "listeners": 22228,
    "playcount": 57523,
    "tags": [
      "dub",
      "reggae"
    ]
  },
  "musicbrainz": {
    "trackMbid": "7cc2cfc6-1f7a-4b3e-9088-3bc736d72d16",
    "artistMbid": "576134a6-9f1f-4bfa-af04-4848195849ca",
    "releaseCount": 3,
    "genres": [
      "dub",
      "reggae"
    ],
    "artistGenres": [
      "dub",
      "reggae",
      "roots reggae"
    ]
  }
}