{
  "youtubeId": "L7XFAqhy-jA",
  "title": "What a Wonderful World",
  "artist": "Sofi Tukker",
  "lastFetched": "2025-11-19T10:35:49.619Z",
  "odesli": {
    "amazonMusic": "B0DD9BTGDJ",
    "amazonStore": "B0DD9BTGDJ",
    "soundcloud": "sofitukker/what-a-wonderful-world",
    "spotify": "5ZLkiDLURiDOLstGhDsHPs",
    "tidal": "381591221",
    "youtube": "L7XFAqhy-jA",
    "youtubeMusic": "L7XFAqhy-jA"
  },
  "artistMbid": "4ac723f4-8be8-4a0d-a3ae-d5dda20f0a9a",
  "lastfm": {
    "id": "Sofi+Tukker/_/What+a+Wonderful+World",
    "listeners": 11899,
    "playcount": 47167,
    "tags": [
      "dance",
      "electronic",
      "pop",
      "indie"
    ]
  }
}