{
  "youtubeId": "mk5Dwg5zm2U",
  "title": "Africa",
  "artist": "Weezer",
  "lastFetched": "2025-11-30T17:44:10.129Z",
  "odesli": {
    "appleMusic": "1388058245",
    "itunes": "1388058245",
    "youtube": "mk5Dwg5zm2U",
    "youtubeMusic": "mk5Dwg5zm2U"
  },
  "lastfm": {
    "summary": "A cover of Toto - Africa featuring \"Weird Al\" Yankovic. Features on Weezer (Teal Album)\n\nIn December 2017 a Twitter account called @weezerafrica started a campaign for Weezer to cover Africa. In May 2018 Weezer responded by covering Rosanna by Toto instead. Eventually in September 2018 Weezer collaborated with \"Weird Al\" Yankovic to cover Africa.\n <a href=\"http://www.last.fm/music/Weezer/_/Africa\">Read more on Last.fm</a>.",
    "id": "Weezer/_/Africa",
    "listeners": 185691,
    "playcount": 1046890,
    "title": "Africa",
    "artist": "Weezer",
    "mbid": "03c5e9f4-0cf4-4253-ab1b-c31c2634e69f",
    "artistMbid": "6fe07aa5-fec0-4eca-a456-f29bff451b04",
    "tags": [
      "cover",
      "pop rock",
      "2018",
      "toto cover"
    ]
  }
}