{
  "youtubeId": "mwycxefNv9Q",
  "title": "Happy and in Love",
  "artist": "Spirits Rejoice",
  "lastFetched": "2025-11-19T17:07:20.381Z",
  "odesli": {
    "amazonMusic": "B0CTMSX6DR",
    "amazonStore": "B0CTMSX6DR",
    "anghami": "1144936122",
    "deezer": "2643134272",
    "appleMusic": "1728434207",
    "itunes": "1728434207",
    "napster": "tra.799365644",
    "pandora": "TR:14852114",
    "soundcloud": "spiritsrejoice/happy-and-in-love",
    "spotify": "44tNuIWaF4icm38qQyOdSk",
    "tidal": "342966736",
    "yandex": "49486487",
    "youtube": "mwycxefNv9Q",
    "youtubeMusic": "mwycxefNv9Q"
  },
  "lastfm": {
    "id": "Spirits+Rejoice/_/Happy+and+in+Love",
    "listeners": 81,
    "playcount": 258,
    "tags": [
      "jazz fusion"
    ]
  },
  "musicbrainz": {
    "artistMbid": "c08b1a71-16ff-4b70-ad28-c74e29d3df78"
  }
}
