{
  "youtubeId": "MzGnX-MbYE4",
  "title": "People Are People",
  "artist": "Depeche Mode",
  "lastFetched": "2025-11-23T16:36:32.701Z",
  "odesli": {
    "amazonMusic": "B073PLBC9V",
    "amazonStore": "B073PLBC9V",
    "audius": "PgrbVgN",
    "anghami": "1042395770",
    "pandora": "TR:6617732",
    "soundcloud": "depeche_mode/people-are-people-remastered",
    "spotify": "4WoKuMjwJXuy9IqX6AH5JE",
    "tidal": "20906974",
    "youtube": "MzGnX-MbYE4",
    "youtubeMusic": "MzGnX-MbYE4"
  },
  "mbid": "5be3cea2-34d0-40f7-97fd-b8d771012a23",
  "lastfmId": "Depeche+Mode/_/People+Are+People",
  "listeners": 526803,
  "playcount": 3280492,
  "artistMbid": "8538e728-ca0b-4321-b7e5-cff6565dd4c0",
  "lastfmSummary": "Written by Martin L. Gore.\nProduced by Daniel Miller & Depeche Mode.\nEngineered by Gareth Jones.\nMixed by Daniel Miller, Gareth Jones & Depeche Mode.\nRecorded at Music Works, London, January 1984.\nMixed at Hansa, Berlin, January 1984. <a href=\"http://www.last.fm/music/Depeche+Mode/_/People+Are+People\">Read more on Last.fm</a>.",
  "musicbrainz": {
    "artistTags": [
      "alternative dance",
      "alternative rock",
      "british",
      "dark wave",
      "electronic",
      "electronic rock",
      "electronica",
      "industrial",
      "new romantic",
      "new wave"
    ],
    "artistGenres": [
      "alternative dance",
      "alternative rock",
      "dark wave",
      "electronic",
      "electronic rock"
    ]
  }
}