{
  "youtubeId": "oE3SzYQDoqs",
  "title": "Kruder & Dorfmeister - Sleazy Rider",
  "lastFetched": "2025-11-26T10:56:54.860Z",
  "ai": {
    "title": "Sleazy Rider",
    "artist": "Kruder & Dorfmeister"
  },
  "lastfm": {
    "id": "Kruder+&+Dorfmeister/_/Sleazy+Rider",
    "listeners": 23616,
    "playcount": 69460,
    "title": "Sleazy Rider",
    "artist": "Kruder & Dorfmeister",
    "mbid": "0afdaac5-00a2-362f-bc96-05b301331671",
    "artistMbid": "6b49dc39-cb6f-465f-980b-bc17a271da34",
    "tags": [
      "secretagent",
      "groovesalad",
      "electronic",
      "drum n bass"
    ]
  }
}