{
  "youtubeId": "OhqzH_ALzZ4",
  "title": "Master of Puppets",
  "artist": "Metallica",
  "lastFetched": "2025-12-02T01:10:30.493Z",
  "musicbrainz": {
    "tags": [
      "thrash metal",
      "metal",
      "heavy metal",
      "metallica",
      "rock"
    ],
    "trackMbid": "18b6c497-d451-4d80-9042-4e2a6d493707",
    "artistMbid": "65f4f0c5-ef9e-490c-aee3-909e7ae6b2ab",
    "releasedAt": "1986-03-03",
    "artistCountry": "US",
    "externalIdsTrack": {
      "spotify": "2MuWTIM3b0YEAskbeeFE1i"
    },
    "externalIdsArtist": {
      "allmusic": "mn0000446509",
      "discogs": "18839",
      "spotify": "2ye2Wgw4gimLv2eAKyk1NB",
      "deezer": "119",
      "lastfm": "Metallica",
      "genius": "Metallica",
      "rateyourmusic": "metallica",
      "soundcloud": "https://soundcloud.com/officialmetallica",
      "napster": "metallica",
      "wikidata": "Q15920",
      "youtube": "UCGexNm_Kw4rdQjLxmpb2EKw"
    }
  },
  "lastfm": {
    "id": "Metallica/_/Master+of+Puppets",
    "listeners": 1573024,
    "playcount": 15884048,
    "summary": "\"Master of Puppets\" is the second song off Metallica's 1986 album \"Master of Puppets\".\n\nThe song, following the theme of control with the rest of the album, discusses drugs and their effects. Addiction, the master referenced in the title, narrates the song, testifying to the destruction that comes from being under the control of drugs. James Hetfield explained  the song \"deals pretty much with drugs. How things get switched around, instead of you controlling what you're taking and doing, it's drugs controlling you. <a href=\"http://www.last.fm/music/Metallica/_/Master+of+Puppets\">Read more on Last.fm</a>.",
    "tags": [
      "thrash metal",
      "metal",
      "heavy metal",
      "metallica"
    ]
  },
  "youtube": {
    "title": "Master of Puppets in the style of Muse [Metallica Cover]",
    "channel": "Andre Antunes"
  }
}