{
  "youtubeId": "Q_QTe1BsbuU",
  "title": "Locomotive",
  "artist": "Mop Mop",
  "lastFetched": "2025-11-23T16:38:18.634Z",
  "odesli": {
    "amazonMusic": "B00LJSQVKK",
    "amazonStore": "B00LJSQVKK",
    "anghami": "20759865",
    "boomplay": "15316450",
    "deezer": "80855736",
    "appleMusic": "896159299",
    "itunes": "896159299",
    "napster": "tra.23513375",
    "pandora": "TR:1465744",
    "soundcloud": "robert-crumb/mop-mop-locomotive",
    "spotify": "72ir6hDoWzut5L4osTVNTR",
    "tidal": "32067653",
    "yandex": "20228146",
    "youtube": "Q_QTe1BsbuU",
    "youtubeMusic": "Q_QTe1BsbuU"
  },
  "mbid": "63b67cbe-7046-38a6-9ef0-a13a12c3206d",
  "artistMbid": "51a4b538-18cc-42aa-87b2-5865e8224af4",
  "musicbrainz": {
    "artistTags": [
      "acid jazz"
    ],
    "artistGenres": [
      "acid jazz"
    ]
  },
  "lastfm": {
    "id": "Mop+Mop/_/Locomotive",
    "listeners": 11383,
    "playcount": 35892,
    "tags": [
      "jazz",
      "lounge",
      "nu jazz",
      "ambient"
    ]
  }
}