{
  "youtubeId": "qV7ha4DO6hU",
  "title": "Piper's Dream - Fred Morrison",
  "artist": "Patrick Molard",
  "lastFetched": "2025-12-02T01:54:18.635Z",
  "odesli": {
    "amazonMusic": "B00F6N4804",
    "amazonStore": "B00F6N4804",
    "appleMusic": "255086816",
    "itunes": "255086816",
    "spotify": "6jJkTbMrhztUggfFLJk8y5",
    "tidal": "41207224",
    "yandex": "14515144",
    "youtube": "qV7ha4DO6hU",
    "youtubeMusic": "qV7ha4DO6hU"
  },
  "lastfm": {
    "id": "Patrick+Molard/_/Piper%27s+Dream+-+Fred+Morrison",
    "listeners": 20,
    "playcount": 22,
    "tags": [
      "folk",
      "celtic",
      "musica",
      "bagpipe"
    ]
  },
  "musicbrainz": {
    "artistMbid": "8f110909-c075-4d54-a253-2a1d510e56ad",
    "trackMbid": "d0f399d3-17d4-4df2-a281-b5b41f5f5759",
    "releaseCount": 1,
    "releasedAt": "2004",
    "artistCountry": "FR",
    "externalIdsArtist": {
      "discogs": "695767",
      "spotify": "5sYA5wDyJQAAnPrrU6oJGZ",
      "lastfm": "Patrick+Molard",
      "wikidata": "Q3369710"
    }
  },
  "youtube": {
    "title": "Piper's Dream - Fred Morrison",
    "channel": "Patrick Molard - Topic"
  }
}