{
  "youtubeId": "rISYCquFeI8",
  "title": "I Just Wanna Live",
  "artist": "Good Charlotte",
  "lastFetched": "2025-12-02T01:55:37.164Z",
  "odesli": {
    "amazonMusic": "B071HYFLWW",
    "amazonStore": "B071HYFLWW",
    "anghami": "61987028",
    "deezer": "7675616",
    "appleMusic": "187457542",
    "itunes": "187457542",
    "pandora": "TR:10104055",
    "soundcloud": "good-charlotte-official/i-just-wanna-live-album",
    "spotify": "5TjwiYZVMHVrGvRzbeCaV7",
    "tidal": "4918655",
    "yandex": "653515",
    "youtube": "rISYCquFeI8",
    "youtubeMusic": "rISYCquFeI8"
  },
  "lastfm": {
    "summary": "\"I Just Wanna Live\" is the second single from Good Charlotte's third studio album, The Chronicles of Life and Death. It was one of the songs that Sony paid radio stations to play in the 2005 payola scandal.  <a href=\"http://www.last.fm/music/Good+Charlotte/_/I+Just+Wanna+Live\">Read more on Last.fm</a>.",
    "id": "Good+Charlotte/_/I+Just+Wanna+Live",
    "listeners": 666437,
    "playcount": 4464220,
    "title": "I Just Wanna Live",
    "artist": "Good Charlotte",
    "mbid": "00e5365c-4f5b-40d5-bd79-99b925291532",
    "artistMbid": "b267ca80-034e-4dc1-9ed4-ec45f1fed41d",
    "tags": [
      "rock",
      "punk rock",
      "alternative",
      "good charlotte",
      "punk"
    ]
  },
  "musicbrainz": {
    "trackMbid": "1ba1927c-b24b-4fe0-ad9b-fe0856b461e2",
    "artistMbid": "b267ca80-034e-4dc1-9ed4-ec45f1fed41d",
    "releaseCount": 25,
    "genres": [
      "blues",
      "pop",
      "punk rock"
    ],
    "artistGenres": [
      "pop punk",
      "post-grunge",
      "punk rock"
    ],
    "releasedAt": "2004-09-28",
    "artistCountry": "US",
    "externalIdsArtist": {
      "allmusic": "mn0000665908",
      "discogs": "261637",
      "spotify": "5aYyPjAsLj7UzANzdupwnS",
      "deezer": "703",
      "lastfm": "Good+Charlotte",
      "genius": "Good-Charlotte",
      "rateyourmusic": "good_charlotte",
      "soundcloud": "https://soundcloud.com/good-charlotte-official",
      "napster": "good-charlotte",
      "wikidata": "Q485220"
    }
  }
}