{
  "youtubeId": "RWgTD_0jxeE",
  "title": "School's Out",
  "artist": "Alice Cooper",
  "lastFetched": "2025-11-24T00:22:28.572Z",
  "odesli": {
    "boomplay": "11315911",
    "deezer": "1957058427",
    "soundcloud": "alicecooperofficial/schools-out-3",
    "spotify": "5vhYDdctoBFmi951xNBvMJ",
    "yandex": "19254046",
    "youtube": "RWgTD_0jxeE",
    "youtubeMusic": "RWgTD_0jxeE"
  },
  "lastfm": {
    "summary": "\"School's Out\" is a 1972 title track single released on Alice Cooper's fifth album,School's Out.\n\nCooper has said he was inspired to write the song when answering the question, \"What's the greatest three minutes of your life?\". Cooper said: \"There's two times during the year. One is Christmas morning, when you're just getting ready to open the presents. The greed factor is right there. The next one is the last three minutes of the last day of school when you're sitting there and it's like a slow fuse burning. <a href=\"http://www.last.fm/music/Alice+Cooper/_/School%27s+Out\">Read more on Last.fm</a>.",
    "id": "Alice+Cooper/_/School%27s+Out",
    "listeners": 717295,
    "playcount": 3263583,
    "title": "School's Out",
    "artist": "Alice Cooper",
    "tags": [
      "classic rock",
      "hard rock",
      "rock",
      "70s",
      "alice cooper"
    ]
  }
}