{
  "youtubeId": "sCJu71JxmbE",
  "title": "Wenn du denkst du denkst dann denkst du nur du denkst",
  "artist": "Juliane Werding",
  "lastFetched": "2025-11-16T20:12:21.117Z",
  "odesli": {
    "amazonMusic": "B0B2QBBV3V",
    "amazonStore": "B0B2QBBV3V",
    "appleMusic": "311194094",
    "itunes": "311194094",
    "pandora": "TR:25040315",
    "soundcloud": "253485378",
    "spotify": "44q8vtBgtjgdBnzmnB0LJj",
    "tidal": "106898",
    "yandex": "39771674",
    "youtube": "sCJu71JxmbE",
    "youtubeMusic": "sCJu71JxmbE"
  }
}