{
  "youtubeId": "tXLhpIUn0H8",
  "title": "Who",
  "artist": "The Montgomery Express",
  "lastFetched": "2025-11-19T17:07:50.894Z",
  "odesli": {
    "amazonMusic": "B000VDZUBU",
    "amazonStore": "B000VDZUBU",
    "soundcloud": "themontgomeryexpress/who",
    "youtube": "tXLhpIUn0H8",
    "youtubeMusic": "tXLhpIUn0H8"
  },
  "mbid": "589e6f11-c3d0-4cd3-98fe-d5fc0bb56335",
  "lastfmId": "The+Montgomery+Express/_/Who",
  "listeners": 4454,
  "playcount": 10396,
  "artistMbid": "1c13a027-cae3-44af-bfcf-be0c6562b91b"
}