{
  "youtubeId": "Ui5X51qcKco",
  "title": "Who Dem?",
  "artist": "Capleton",
  "lastFetched": "2025-11-23T20:22:29.869Z",
  "odesli": {
    "amazonMusic": "B000X7S4QC",
    "amazonStore": "B000X7S4QC",
    "audiomack": "60053398",
    "anghami": "27360207",
    "boomplay": "4177240",
    "deezer": "63413281",
    "appleMusic": "310539573",
    "itunes": "310539573",
    "napster": "tra.54713621",
    "pandora": "TR:1532554",
    "soundcloud": "capleton-official/who-dem",
    "tidal": "2523541",
    "youtube": "Ui5X51qcKco",
    "youtubeMusic": "Ui5X51qcKco"
  }
}