{
  "youtubeId": "VKzWLUQizz8",
  "title": "Genesis",
  "artist": "Justice",
  "lastFetched": "2025-11-23T16:40:51.271Z",
  "odesli": {
    "amazonMusic": "B073HJF4YY",
    "amazonStore": "B073HJF4YY",
    "audiomack": "25514062",
    "anghami": "1087954374",
    "boomplay": "8216314",
    "deezer": "10284907",
    "appleMusic": "259751738",
    "itunes": "259751738",
    "napster": "tra.135184796",
    "pandora": "TR:83651872",
    "soundcloud": "justice-official/genesis",
    "spotify": "4wSmqFg31t6LsQWtzYAJob",
    "tidal": "43421708",
    "yandex": "432793",
    "youtube": "VKzWLUQizz8",
    "youtubeMusic": "VKzWLUQizz8"
  },
  "mbid": "01492e36-f10e-48ca-8d5c-4aa120da646b",
  "artistMbid": "860b2707-6153-4e3a-aa57-74d2b42c55b5",
  "musicbrainz": {
    "artistTags": [
      "dance",
      "electro",
      "electro house",
      "electro-disco",
      "electronic",
      "european",
      "france",
      "français",
      "french",
      "french electro"
    ],
    "artistGenres": [
      "dance",
      "electro",
      "electro house",
      "electro-disco",
      "electronic"
    ]
  },
  "lastfm": {
    "id": "Justice/_/Genesis",
    "listeners": 969378,
    "playcount": 7110491,
    "summary": "“Genesis“ is a track by French electronic duo Justice. They borrowed the hand clap from 50 Cent's \"In Da Club,\" plus samples of Slipknot and Queen. However, none of them are credited. De Rosnay explained to MTV News that this was because, \"they are such short samples no one can recognize them. The ones from Slipknot, for example, are just tiny bits of the voice.\"\n\nAmong the television shows this has featured in are the CBS legal drama Shark and the BBC documentary series Doctor Who Confidential. <a href=\"http://www.last.fm/music/Justice/_/Genesis\">Read more on Last.fm</a>.",
    "tags": [
      "electronic",
      "electro",
      "dance",
      "french",
      "house"
    ]
  }
}