{
  "youtubeId": "YfjTZLxekig",
  "title": "Click Click Boom",
  "artist": "Saliva",
  "lastFetched": "2025-12-02T01:26:28.376Z",
  "odesli": {
    "amazonMusic": "B07G8GVHSX",
    "amazonStore": "B07G8GVHSX",
    "anghami": "2732160",
    "boomplay": "2615311",
    "pandora": "TR:81652",
    "soundcloud": "saliva/click-click-boom",
    "spotify": "2CGDxXXYbkPOyRXHzQbqkT",
    "tidal": "93170558",
    "yandex": "365622",
    "youtube": "YfjTZLxekig",
    "youtubeMusic": "YfjTZLxekig"
  },
  "musicbrainz": {
    "tags": [
      "hard rock",
      "rock",
      "Nu Metal",
      "Saliva",
      "metal"
    ],
    "trackMbid": "6befa91f-fce9-4582-95f5-dc07f19a881c",
    "artistMbid": "6e650a01-6489-4dc8-85e1-8ec809dd72a2",
    "releasedAt": "2000",
    "artistCountry": "US",
    "externalIdsTrack": {
      "spotify": "2CGDxXXYbkPOyRXHzQbqkT"
    },
    "externalIdsArtist": {
      "allmusic": "mn0000242211",
      "bandcamp": "https://officialsaliva.bandcamp.com/",
      "discogs": "93052",
      "spotify": "5S6hjAxgxjsLylsTtMIimO",
      "deezer": "3117",
      "lastfm": "Saliva",
      "genius": "Saliva",
      "rateyourmusic": "saliva",
      "soundcloud": "https://soundcloud.com/saliva",
      "napster": "saliva",
      "wikidata": "Q1753914",
      "youtube": "UCzjMi7EaV2L5dYvH-_FQ4ow"
    }
  },
  "lastfm": {
    "id": "Saliva/_/Click+Click+Boom",
    "listeners": 560551,
    "playcount": 3232000,
    "summary": "\"Click Click Boom\" is a song by American rock band Saliva. It was released in 2001 on their second album Every Six Seconds as the lead single. The song was later re-recorded, entitled \"Click Click Pull\", in response to the September 11, 2001 attacks.\n\n    * Official theme song for WWF No Mercy 2001.\n    * Used in the films; The Fast and the Furious (although it was not on the main OST, however the song's music video can be found on the Special Edition DVD release) <a href=\"http://www.last.fm/music/Saliva/_/Click+Click+Boom\">Read more on Last.fm</a>.",
    "tags": [
      "hard rock",
      "rock",
      "nu metal",
      "saliva",
      "metal"
    ]
  }
}