{
  "youtubeId": "yQOBUrRaPU0",
  "title": "Name",
  "lastFetched": "2025-12-02T02:06:05.020Z",
  "ai": {
    "title": "Name",
    "artist": "Goo Goo Dolls"
  },
  "odesli": {
    "amazonMusic": "B07VYLDTDW",
    "amazonStore": "B07VYLDTDW",
    "audiomack": "21574241",
    "anghami": "417612",
    "boomplay": "4677367",
    "deezer": "775475",
    "appleMusic": "1109657724",
    "itunes": "1109657724",
    "napster": "tra.1960410",
    "pandora": "TR:153757129",
    "soundcloud": "thegoogoodolls/name",
    "spotify": "1G8jae4jD8mwkXdodqHsBM",
    "tidal": "391273",
    "yandex": "215413",
    "youtube": "yQOBUrRaPU0",
    "youtubeMusic": "yQOBUrRaPU0"
  },
  "artist": "The Goo Goo Dolls",
  "musicbrainz": {
    "trackMbid": "4bcc68b6-8e31-4303-ab54-a3f2956ded4c",
    "artistMbid": "e2c00c56-8365-4160-9f40-a64682917633",
    "releaseCount": 2,
    "artistGenres": [
      "acoustic rock",
      "alternative rock",
      "hardcore punk",
      "jangle pop",
      "pop punk",
      "pop rock",
      "post-grunge",
      "power pop",
      "punk rock",
      "soft rock"
    ],
    "releasedAt": "1996",
    "artistCountry": "US",
    "externalIdsArtist": {
      "allmusic": "mn0000949630",
      "discogs": "252661",
      "spotify": "2sil8z5kiy4r76CRTXxBCA",
      "deezer": "65791",
      "lastfm": "Goo+Goo+Dolls",
      "genius": "Goo-goo-dolls",
      "rateyourmusic": "goo-goo-dolls",
      "soundcloud": "https://soundcloud.com/thegoogoodolls",
      "wikidata": "Q730046",
      "youtube": "UCjOkbXu7vYeeQrA7R3-OfXQ"
    }
  },
  "youtube": {
    "title": "Goo Goo Dolls - Name [Official Music Video] (HD Remaster)",
    "channel": "Goo Goo Dolls"
  }
}