{
  "youtubeId": "ZAuIFXMwyaE",
  "title": "Jiggery Pokery by The Duckworth Lewis Method animation",
  "lastFetched": "2025-11-26T10:57:05.131Z",
  "ai": {
    "title": "Jiggery Pokery",
    "artist": "The Duckworth Lewis Method"
  },
  "lastfm": {
    "id": "The+Duckworth+Lewis+Method/_/Jiggery+Pokery",
    "listeners": 9857,
    "playcount": 54264,
    "title": "Jiggery Pokery",
    "artist": "The Duckworth Lewis Method",
    "mbid": "46fe300d-ec47-42ab-b07d-e1072d5ef6db",
    "artistMbid": "52039241-8f7a-4d19-b77b-83011d9d4bec",
    "tags": [
      "indie pop",
      "pop",
      "best of 2009",
      "chamber pop",
      "aussie skulduggery"
    ]
  }
}