{
  "youtubeId": "ZckaCTKFBXU",
  "title": "Clap Your Hands",
  "artist": "Kungs",
  "lastFetched": "2025-12-02T01:27:51.375Z",
  "odesli": {
    "amazonMusic": "B0013AF628",
    "amazonStore": "B0013AF628",
    "audius": "JPg1k",
    "anghami": "1059606136",
    "boomplay": "83603363",
    "pandora": "TR:100141443",
    "soundcloud": "kungsmusic/clap-your-hands",
    "spotify": "7g7OshelYRRnOSEMmisJVI",
    "tidal": "220326055",
    "yandex": "101224806",
    "youtube": "ZckaCTKFBXU",
    "youtubeMusic": "ZckaCTKFBXU"
  },
  "lastfm": {
    "id": "Kungs/_/Clap+Your+Hands",
    "listeners": 70077,
    "playcount": 378649,
    "tags": [
      "french",
      "pop",
      "house",
      "dance",
      "cover"
    ]
  },
  "musicbrainz": {
    "trackMbid": "d4c4b35f-1f11-4738-8eff-a7a06f1f0624",
    "artistMbid": "a125cd83-a379-4935-a7ec-beaa778bad70",
    "releaseCount": 25,
    "genres": [
      "pop"
    ],
    "artistGenres": [
      "deep house",
      "edm",
      "house",
      "tropical house"
    ],
    "releasedAt": "2022-02-18",
    "artistCountry": "FR",
    "externalIdsTrack": {
      "spotify": "3vYkOXwIVmcMuuiNTM6tYR",
      "deezer": "1802218997"
    },
    "externalIdsArtist": {
      "allmusic": "mn0003417741",
      "discogs": "4394625",
      "spotify": "7keGfmQR4X5w0two1xKZ7d",
      "deezer": "5992092",
      "lastfm": "Kungs",
      "genius": "Kungs",
      "rateyourmusic": "kungs",
      "soundcloud": "https://soundcloud.com/kungsmusic",
      "wikidata": "Q23826199",
      "youtube": "UCdaQq_IggxNXTvW2HV1GXRQ"
    }
  }
}